common_setup.py
ez_setup.py
setup.py