Metadata-Version: 1.0
Name: workshop
Version: 0.0.0
Summary: webAppWorkshop tools and dependencies
Home-page: UNKNOWN
Author: Sabren Enterprises, Inc.
Author-email: help@webappworkshop.com
License: LGPL
Platform: UNKNOWN
